<?xml version="1.0" encoding="utf-8"?>
<Sessions xmlns:xsi="http://www.w3.org/2001/XMLSchema-instance" xsi:noNamespaceSchemaLocatio="./Session.xsd">
  <Session id="1" date="12/12/2024" class="A" teacherId="3" classID="1">
    <AttendenceRecord>
      <stdid>5</stdid>
      <stdName>Ahmed</stdName>
      <status>notAsssigned</status>
    </AttendenceRecord>
    <AttendenceRecord>
      <stdid>6</stdid>
      <stdName>Ali</stdName>
      <status>notAsssigned</status>
    </AttendenceRecord>
    <AttendenceRecord>
      <stdid>7</stdid>
      <stdName>Kamil</stdName>
      <status>notAsssigned</status>
    </AttendenceRecord>
  </Session>
  <Session id="2" date="24/12/2024" class="A" teacherId="3" classID="1">
    <AttendenceRecord>
      <stdid>5</stdid>
      <stdName>Ahmed</stdName>
      <status>notAsssigned</status>
    </AttendenceRecord>
    <AttendenceRecord>
      <stdid>6</stdid>
      <stdName>Ali</stdName>
      <status>notAsssigned</status>
    </AttendenceRecord>
    <AttendenceRecord>
      <stdid>7</stdid>
      <stdName>Kamil</stdName>
      <status>notAsssigned</status>
    </AttendenceRecord>
  </Session>
  <Session id="3" date="12/05/2020" subjectId="12" class="sql" teacherId="26" classID="1">
    <AttendenceRecord>
      <stdid>9</stdid>
      <stdName>mmm</stdName>
      <status>notAsssigned</status>
    </AttendenceRecord>
  </Session>
  <Session id="4" date="22/02/2024" subjectId="6" class="kkk" teacherId="3" />
  <Session id="5" date="24/02/2024" subjectId="4" class="html" teacherId="3" />
  <Session id="6" date="31/12/2024" subjectId="4" class="html" teacherId="3">
    <AttendenceRecord>
      <stdid>2</stdid>
      <stdName>alice_smith</stdName>
      <status>notAsssigned</status>
    </AttendenceRecord>
  </Session>
</Sessions>